[
  {
    "question": "What is your main goal from practicing sports?",
    "options": ["Improve general fitness", "Build muscles", "Fun and enjoyment", "Competition and challenge", "Stress relief"]
  },
  {
    "question": "Where do you prefer to exercise?",
    "options": ["Outdoors", "In the gym", "At home", "Doesn't matter"]
  },
  {
    "question": "Do you like sports that require mental focus?",
    "options": ["Yes", "No", "Sometimes"]
  },
  {
    "question": "How competitive are you?",
    "options": ["I love competition", "I dislike competition", "Depends on mood"]
  }
]